raxo/__init__.py
raxo/core/__init__.py
raxo/core/base.py
raxo/databases/__init__.py
raxo/databases/mysql_connector.py
raxo/databases/vertica_connector.py
raxo/embeddings/__init__.py
raxo/embeddings/azure_embedding.py
raxo/embeddings/embedding.py
raxo/embeddings/openai_embedding.py
raxo/models/__init__.py
raxo/models/azure_chat.py
raxo/models/llms.py
raxo/models/openai_chat.py
raxo/utils/__init__.py
raxo/utils/exceptions.py
raxo/utils/prompts.py
raxo/utils/sql_utils.py
raxo/vector/__init__.py
raxo/vector/chroma_db.py
raxo/vector/vector.py
raxo-0.0.4.1.dist-info/LICENSE
raxo-0.0.4.1.dist-info/WHEEL
raxo-0.0.4.1.dist-info/METADATA
raxo-0.0.4.1.dist-info/RECORD
