Metadata-Version: 2.1
Name: raxo
Version: 0.0.4.1
Summary: Raxo is a Python package designed to streamline the process of converting natural language queries
Author-email: Bipul Kumar Singh <bipulsinghkashyap@gmail.com>, Prashant Tomar <prashanttomar7000@gmail.com>
Requires-Python: >=3.9
Classifier: Programming Language :: Python :: 3
Classifier: License :: OSI Approved :: MIT License
Classifier: Operating System :: OS Independent
Requires-Dist: openai >= 1.30.1
Requires-Dist: chromadb >= 0.5.0
Requires-Dist: mysql-connector-python >= 8.4.0 ; extra == "mysql"
Requires-Dist: vertica-python >= 1.3.8 ; extra == "vertica"
Project-URL: Bug Tracker, https://github.com/raxo-ai/raxo/issues
Project-URL: Homepage, https://github.com/raxo-ai/raxo
Provides-Extra: mysql
Provides-Extra: vertica
